rtgym/__init__.py
rtgym/envs/__init__.py
rtgym/envs/real_time_env.py
rtgym/envs/utils/__init__.py
rtgym/envs/utils/benchmark.py
rtgym/tuto/__init__.py
rtgym/tuto/dummy_drone.py
rtgym/tuto/tuto.py
rtgym-0.16.dist-info/licenses/LICENSE
rtgym-0.16.dist-info/METADATA
rtgym-0.16.dist-info/WHEEL
rtgym-0.16.dist-info/top_level.txt
rtgym-0.16.dist-info/RECORD
