Metadata-Version: 2.4
Name: rtgym
Version: 0.16
Summary: Easily implement custom Gymnasium environments for real-time applications
Home-page: https://github.com/yannbouteiller/rtgym
Download-URL: https://github.com/yannbouteiller/rtgym/archive/refs/tags/v0.16.tar.gz
Author: Yann Bouteiller
License: MIT
Keywords: gymnasium,real,time,custom,environment,reinforcement,learning,random,delays
Classifier: Development Status :: 5 - Production/Stable
Classifier: Intended Audience :: Developers
Classifier: Intended Audience :: Education
Classifier: Intended Audience :: Information Technology
Classifier: Intended Audience :: Science/Research
Classifier: Operating System :: Microsoft :: Windows
Classifier: Operating System :: POSIX
Classifier: Programming Language :: Python
Classifier: Topic :: Scientific/Engineering :: Artificial Intelligence
License-File: LICENSE
Requires-Dist: gymnasium>=1.0.0
Requires-Dist: numpy
Dynamic: author
Dynamic: classifier
Dynamic: description
Dynamic: description-content-type
Dynamic: download-url
Dynamic: home-page
Dynamic: keywords
Dynamic: license
Dynamic: license-file
Dynamic: requires-dist
Dynamic: summary
